[
  {
    "id": 1,
    "Servicerequested": "TOWING SERVICE OF ENGINE",
    "chargeable": "Y",
    "Customer": "DHL",
    "CustomerName": "DHL",
    "AWBNumber": "618-98877800",
    "ULDNumber": "",
    "FlightDate": "",
    "RequestedDate": "",
    "RequestedBy": "",
    "Tracter": "",
    "Startdate": "",
    "Starttime": "",
    "Completeddate": "",
    "Completedtime": "",
    "Remarks": "",
    "Status": "Pending",
    "ReasonforRejection": "",
    "Documentname": "",
    "Documents": ""
  },
  {
    "id": 2,
    "Servicerequested": "FORKLIFT RENTAL",
    "chargeable": "Y",
    "Customer": "DBS",
    "CustomerName": "DHL",
    "AWBNumber": "318-22110118",
    "ULDNumber": "AKE10011SQ",
    "FlightDate": "SQ666 06SEP2017",
    "RequestedDate": "05SEP2017 13:10",
    "RequestedBy": "",
    "Tracter": "",
    "Startdate": "",
    "Starttime": "",
    "Completeddate": "",
    "Completedtime": "",
    "Remarks": "success",
    "Status": "Completed",
    "ReasonforRejection": "",
    "Documentname": "",
    "Documents": ""
  },
  {
    "id": 3,
    "Servicerequested": "SECURITY ESCORT",
    "chargeable": "Y",
    "Customer": "TNT",
    "CustomerName": "DHL",
    "AWBNumber": "618-77661001",
    "ULDNumber": "",
    "FlightDate": "",
    "RequestedDate": "",
    "RequestedBy": "",
    "Tracter": "",
    "Startdate": "",
    "Starttime": "",
    "Completeddate": "",
    "Completedtime": "",
    "Remarks": "",
    "Status": "Rejected",
    "ReasonforRejection": "Late Lodge-in",
    "Documentname": "",
    "Documents": ""
  },
  {
    "id": 4,
    "Servicerequested": "APPLY PERMIT",
    "chargeable": "Y",
    "Customer": "NES",
    "CustomerName": "DHL",
    "AWBNumber": "618-10012211",
    "ULDNumber": "",
    "FlightDate": "SQ767 07SEP2017",
    "RequestedDate": "06SEP2017 10:00",
    "RequestedBy": "",
    "Tracter": "",
    "Startdate": "",
    "Starttime": "",
    "Completeddate": "",
    "Completedtime": "",
    "Remarks": "",
    "Status": "Pending",
    "ReasonforRejection": "",
    "Documentname": "",
    "Documents": ""
  },
  {
    "id": 5,
    "Servicerequested": "TOPUP DRY ICE",
    "chargeable": "Y",
    "Customer": "DHL",
    "CustomerName": "DHL",
    "AWBNumber": "618-33221001",
    "ULDNumber": "",
    "FlightDate": "",
    "RequestedDate": "",
    "RequestedBy": "",
    "Tracter": "",
    "Startdate": "",
    "Starttime": "",
    "Completeddate": "",
    "Completedtime": "",
    "Remarks": "",
    "Status": "Started",
    "ReasonforRejection": "",
    "Documentname": "",
    "Documents": ""
  },
  {
    "id": 6,
    "Servicerequested": "FORKLIFT RENTAL",
    "chargeable": "Y",
    "Customer": "DBS",
    "CustomerName": "DHL",
    "AWBNumber": "318-22110118",
    "ULDNumber": "AKE10011SQ",
    "FlightDate": "SQ666 06SEP2017",
    "RequestedDate": "05SEP2017 13:10",
    "RequestedBy": "Dineshbabu",
    "Tracter": "4",
    "Startdate": "06SEP2018",
    "Starttime": "13:10",
    "Completeddate": "07SEP2017",
    "Completedtime": "14:10",
    "Remarks": "success",
    "Status": "Completed",
    "ReasonforRejection": "Late Lodge-in",
    "Documentname": "AAdharcard",
    "Documents": "dsf"
  }
]
